vfx_generate/__init__.py
vfx_generate/main.py
vfx_generate-0.0.1.dist-info/LICENSE
vfx_generate-0.0.1.dist-info/METADATA
vfx_generate-0.0.1.dist-info/WHEEL
vfx_generate-0.0.1.dist-info/top_level.txt
vfx_generate-0.0.1.dist-info/RECORD
