Metadata-Version: 2.1
Name: vfx-generate
Version: 0.0.1
Summary: A brief description of your package
Home-page: https://github.com/KawaguchiYui
Author: yuikawaguchi
Author-email: s2222011@stu.musashino-u.ac.jp
License: UNKNOWN
Platform: UNKNOWN
Classifier: Programming Language :: Python :: 3
Classifier: License :: OSI Approved :: MIT License
Classifier: Operating System :: OS Independent
Requires-Python: >=3.6
License-File: LICENSE
Requires-Dist: pandas
Requires-Dist: numpy
Requires-Dist: Pillow
